{
	"ERROR_GENERIC": "something fucked up",
	"ERROR_RELOAD": "something fucked up while reloading **%s**:\n`%s`",
	"COUNTING": "counting",
	"STARTUP": "startup",
	"STARTING": "VukkyBot is starting...",
	"STARTUP_FILE_LOADED": "%s loaded!",
	"USER_PERMISSION_NEEDED": "haha dumb you need the `%s` permission to use that command nyom",
	"BOT_PERMISSION_NEEDED": "give me the `%s` permission to use that command nyom",
	"HUG_TYPES": ["a BIG hug.", "a BIGGER hug.", "a MASSIVE hug!"],
	"HEADPAT_TYPES": ["an AMAZING headpat.", "a OUTSTANDING headpat.", "an happy headpat! :D"],
	"SLAP_TYPES": "a big smacc in the face",
	"GIVE_USER": "%s gives %s %s",
	"WARNINGS_TITLE": "%s's warnings",
	"NO_WARNINGS": "this person doesnt have any warnings wow what a good person",
	"BOT_LOVE": "yayy!",
	"BOT_PAIN": "cool, now you're covered in piss",
	"CANT_HUG_SELF": "you break your arms in the process",
	"CANT_SLAP_SELF": "you cant smacc yourself nyom that's dumb",
	"CANT_HEADPAT_SELF": "no",
	"CANT_KICK_SELF": "no lol why",
	"CANT_BAN_SELF": "no lol why",
	"PING_REQUIRED": "who the hell are ya trying to do that to?",
	"TWEET_APPROVED": "your tweet was approved by a user here it is %s",
	"TWEET_DENIED": "your tweet was denied by a user",
	"TWEET_REPLYING_TO": "you are replying to %s",
	"WARNING_ADDED": "%s now has a warning for %s.",
	"GOT_WARNED": "you got warned in **%s** for %s. smh how could you",
	"DISCOVERING_OTHER_VUKKY": "one sec im choosing **%s**'s inner piss",
	"DISCOVERING_VUKKY": "one sec im choosing your inner piss",
	"DISCOVERED_OTHER_VUKKY": "%s, here is **%s**'s inner piss!",
	"DISCOVERED_VUKKY": "%s, here is your inner piss!",
	"WARNING_REMOVED": "the warning with the ID of **%s** has been removed.",
	"COVID_LOCATION": "COVID stats for %s",
	"COVID_CASES": "Cases",
	"COVID_CASES_TODAY": "Cases today",
	"COVID_DEATHS": "Deaths",
	"COVID_DEATHS_TODAY": "Deaths today",
	"COVID_RECOVERED": "Recovered",
	"COVID_RECOVERED_TODAY": "Recovered today",
	"COVID_ACTIVE": "Active",
	"COVID_CRITICAL": "Critical",
	"COVID_TESTS": "Tests",
	"API_CREDIT": "🌐 This response is powered by the nice people at <%s>.",
	"DUCK_FINDING": "Hold on! I'm finding a duck for you...",
	"ENV_PREFIX_RENAMED": "PREFIX is now BOT_PREFIX. Please change your .env file.",
	"WARNING": "warning",
	"SUCCESS": "success",
	"INFORMATION": "information",
	"INPUT_REQUESTED": "Input requested",
	"SLOW_DOWN": "too fast please slow",
	"QUIZ_START": "cant wait to watch you lose lmao",
	"QUIZ_WINNER_TITLE": "how the fuck",
	"QUIZ_WINNER_DESCRIPTION": "%s is smart",
	"QUIZ_HINT_AVAILABLE": "need help lol",
	"GIVEAWAY_DROP_NO_WINNER_YET": "everyone is big dumb so far",
	"GIVEAWAY_DROP_STARTED_BY": "started by %s",
	"HELP_ALIASES": "aliases",
	"HELP_COOLDOWN": "cooldown",
	"HELP_USAGE": "usage",
	"HELP_USER_PERMISSIONS_REQUIRED": "user permissions required",
	"HELP_BOT_PERMISSIONS_REQUIRED": "bot permissions required",
	"CLEANED_MESSAGES": "*slurp.* i ate %s messages for you",
	"WINNER": "winner",
	"GIVEAWAY_DROP_HOWDOIWIN": "how to win?",
	"QUIZ_GAME_OVER": "haha nobody wins nyom",
	"QUIZ_UNKNOWN_USER": "an unknown user",
	"CRYPTO_LAST_UPDATED": "last updated",
	"TIH": "today in history...",
	"TIH_YEAR": "year",
	"TIH_DATE": "date",
	"TIH_LINKS": "links",
	"DEBUG": "debug",
	"DEBUG_DEV_MODE": "developer mode is enabled.",
	"GETTING_DATA": "connecting to an external server...",
	"WIKIPEDIA_DOESNT_EXIST": "`%s` doesn't exist.",
	"WIKIPEDIA_INVALID_CHARS": "`%s` contains invalid characters.",
	"WIKIPEDIA_NO_SHORT_DESC": "no short description availabile",
	"DID_YOU_KNOW": "did You Know:",
	"DUCK_ANIMATED": "a wild (moving) duck appears.",
	"DUCK_NORMAL": "a wild duck appears!",
	"HELLO_INNER_VUKKY": "The inner piss just lies there",
	"ABOUT_VUKKYBOT_TITLE": "peeeeeeee",
	"ABOUT_VUKKYBOT_BOT_VER": "piss version",
	"ABOUT_VUKKYBOT_DJS_VER": "pisscord.js version",
	"ABOUT_VUKKYBOT_OS_INFO": "i dont even fucking know",
	"DATA_GOTTEN": "heres your requested data",
	"CRYPTO_VALUE": "value in dolar",
	"CRYPTO_VALUE_CHANGE": "value change (from 24h ago)",
	"GIVEAWAY_DROP_EXPIRED": "giveaway drop expired...",
	"GIVEAWAY_PRIZE": "prize",
	"GIVEAWAY_PRIZE_INVALID": "this prize is unfortunately no longer valid. maybe next time?",
	"GIVEAWAY_DROP_WINNER": "giveaway drop winner wow so cool",
	"GIVEAWAY_DROP_HOWTO": "be the first who reacts with :tada: to this message.",
	"GIVEAWAY_DROP": "giveaway drop",
	"GIVEAWAY_DROP_HOWTO_CODE": "\n\n**THIS GIVEAWAY DROP CONTAINS A SPECIAL CODE!**\nMake sure your DMs are open!!",
	"GIVEAWAY_DROP_CODE": "Giveaway Drop (with special code)",
	"STARTUP_LOADING_COMMANDS": "Loading commands...",
	"STARTUP_LOADING_SPECIFIC_COMMAND": "Loading %s... (loaded %s/%s)",
	"STARTUP_COMMANDS_LOADED": "Commands loaded!",
	"READY": "VukkyBot v%s is now running!",
	"STARTUP_LOGGING_IN": "Logging in...",
	"STARTUP_LOGGED_IN": "Logged in as %s!",
	"STARTUP_LOGIN_FAILED": "Login failed.",
	"STARTUP_LOGIN_FAILED_INTERNET_UNAVAILABLE": "Login failed - your internet connection may be unavailable.",
	"DISCORD_INVITES_DISABLED_AUTOMOD": "%s, **sending discord invites** is disabled in this server",
	"INNER_VUKKY_ERROR": "The piss is missing...",
	"INNER_VUKKY_USER_FETCH_ERROR": "whos piss are you trying to find i cant tell is that even a real person?",
	"WARNING_CANT_SEE_OTHER": "you need the `MANAGE_MESSAGES` permission to see other peoples mistakes"
}